jupyter_suggestions_core/__init__.py
jupyter_suggestions_core/_version.py
jupyter_suggestions_core-0.1.1.data/data/share/jupyter/labextensions/@jupyter/suggestions-core/package.json
jupyter_suggestions_core-0.1.1.data/data/share/jupyter/labextensions/@jupyter/suggestions-core/schemas/@jupyter/suggestions-core/commands.json
jupyter_suggestions_core-0.1.1.data/data/share/jupyter/labextensions/@jupyter/suggestions-core/schemas/@jupyter/suggestions-core/package.json.orig
jupyter_suggestions_core-0.1.1.data/data/share/jupyter/labextensions/@jupyter/suggestions-core/schemas/@jupyter/suggestions-core/registry.json
jupyter_suggestions_core-0.1.1.data/data/share/jupyter/labextensions/@jupyter/suggestions-core/static/319.499f88809e516b0438b6.js
jupyter_suggestions_core-0.1.1.data/data/share/jupyter/labextensions/@jupyter/suggestions-core/static/405.f6d38aef780fc99bdef3.js
jupyter_suggestions_core-0.1.1.data/data/share/jupyter/labextensions/@jupyter/suggestions-core/static/432.ad5c8fd5d3beaf42cb96.js
jupyter_suggestions_core-0.1.1.data/data/share/jupyter/labextensions/@jupyter/suggestions-core/static/759.185d828d84d2d6787577.js
jupyter_suggestions_core-0.1.1.data/data/share/jupyter/labextensions/@jupyter/suggestions-core/static/977.cd2040e395ac27219873.js
jupyter_suggestions_core-0.1.1.data/data/share/jupyter/labextensions/@jupyter/suggestions-core/static/remoteEntry.dd761004a788c616d579.js
jupyter_suggestions_core-0.1.1.data/data/share/jupyter/labextensions/@jupyter/suggestions-core/static/style.js
jupyter_suggestions_core-0.1.1.data/data/share/jupyter/labextensions/@jupyter/suggestions-core/static/third-party-licenses.json
jupyter_suggestions_core-0.1.1.data/data/share/jupyter/labextensions/@jupyter/suggestions-core/install.json
jupyter_suggestions_core-0.1.1.dist-info/METADATA
jupyter_suggestions_core-0.1.1.dist-info/WHEEL
jupyter_suggestions_core-0.1.1.dist-info/licenses/LICENSE
jupyter_suggestions_core-0.1.1.dist-info/RECORD
