Metadata-Version: 2.4
Name: jupyter_suggestions_core
Version: 0.1.1
Dynamic: Keywords
Summary: Jupyter Suggestions core extension
Project-URL: Homepage, https://github.com/jupyterlab-contrib/jupyter-suggestions
Project-URL: Bug Tracker, https://github.com/jupyterlab-contrib/jupyter-suggestions/issues
Project-URL: Repository, https://github.com/jupyterlab-contrib/jupyter-suggestions.git
Author: QuantStack
License: BSD 3-Clause License
License-File: LICENSE
Classifier: Framework :: Jupyter
Classifier: Framework :: Jupyter :: JupyterLab
Classifier: Framework :: Jupyter :: JupyterLab :: 4
Classifier: Framework :: Jupyter :: JupyterLab :: Extensions
Classifier: Framework :: Jupyter :: JupyterLab :: Extensions :: Prebuilt
Classifier: License :: OSI Approved :: BSD License
Classifier: Programming Language :: Python
Classifier: Programming Language :: Python :: 3
Classifier: Programming Language :: Python :: 3.8
Classifier: Programming Language :: Python :: 3.9
Classifier: Programming Language :: Python :: 3.10
Classifier: Programming Language :: Python :: 3.11
Classifier: Programming Language :: Python :: 3.12
Requires-Python: >=3.9
